ignoreTests/conftest.py
ignoreTests/auth/login.py
ignoreTests/store/cred_store.py
pyntcli/__init__.py
pyntcli/main.py
pyntcli/analytics/__init__.py
pyntcli/analytics/send.py
pyntcli/auth/__init__.py
pyntcli/auth/login.py
pyntcli/commands/__init__.py
pyntcli/commands/burp.py
pyntcli/commands/command.py
pyntcli/commands/har.py
pyntcli/commands/id_command.py
pyntcli/commands/listen.py
pyntcli/commands/newman.py
pyntcli/commands/postman.py
pyntcli/commands/pynt_cmd.py
pyntcli/commands/root.py
pyntcli/commands/static_file_extensions.py
pyntcli/commands/sub_command.py
pyntcli/commands/template.py
pyntcli/commands/util.py
pyntcli/log/__init__.py
pyntcli/log/log.py
pyntcli/pynt_docker/__init__.py
pyntcli/pynt_docker/container_utils.py
pyntcli/pynt_docker/pynt_container.py
pyntcli/saas_client/__init__.py
pyntcli/saas_client/saas_client.py
pyntcli/store/__init__.py
pyntcli/store/json_connector.py
pyntcli/store/store.py
pyntcli/store/store_connector.py
pyntcli/transport/__init__.py
pyntcli/transport/pynt_requests.py
pyntcli/ui/__init__.py
pyntcli/ui/progress.py
pyntcli/ui/prompt.py
pyntcli/ui/pynt_errors.py
pyntcli/ui/report.py
pyntcli/ui/ui_thread.py
tests/test_utils.py
tests/commands/test_pynt_cmd.py
pyntcli-0.1.123.dist-info/METADATA
pyntcli-0.1.123.dist-info/WHEEL
pyntcli-0.1.123.dist-info/entry_points.txt
pyntcli-0.1.123.dist-info/top_level.txt
pyntcli-0.1.123.dist-info/RECORD
