Metadata-Version: 2.4
Name: pyntcli
Version: 0.1.123
Summary: Command line utility to handle all of Pynt's different integrations
Author-email: Pynt-io <support@pynt.io>
Project-URL: Homepage, https://pynt.io
Requires-Python: >=3.9
Requires-Dist: rich
Requires-Dist: requests==2.31.0
Requires-Dist: pem
Requires-Dist: certifi>=2017.4.17
Requires-Dist: websocket-client
Requires-Dist: xmltodict
Requires-Dist: timedinput==0.1.1
